voiceads/__init__.py
voiceads/voiceads.py
voiceads-0.0.5.dist-info/DESCRIPTION.rst
voiceads-0.0.5.dist-info/METADATA
voiceads-0.0.5.dist-info/RECORD
voiceads-0.0.5.dist-info/WHEEL
voiceads-0.0.5.dist-info/metadata.json
voiceads-0.0.5.dist-info/top_level.txt
