Metadata-Version: 2.0
Name: voiceads
Version: 0.0.5
Summary: VoiceAds.ai Python SDK
Home-page: https://bitbucket.org/voiceadsai/voiceads-python-sdk
Author: Anupam Jain
Author-email: tech@voiceads.ai
License: MIT
Keywords: voiceads,voiceads.ai,alexasdk
Platform: UNKNOWN
Classifier: Intended Audience :: Developers
Classifier: Topic :: Software Development :: Build Tools
Classifier: License :: OSI Approved :: MIT License
Classifier: Programming Language :: Python :: 2.7
Requires-Dist: requests
